{"BaseModel.1a7baa56-85a2-4241-abfc-0bbd7813640e": {"id": "1a7baa56-85a2-4241-abfc-0bbd7813640e", "created_at": "2022-10-29T21:06:19.797111", "updated_at": "2022-10-29T21:06:19.797157", "name": "My First Model", "my_number": 89, "__class__": "BaseModel"}, "User.507a28ae-df7d-45e3-8499-0c1c04631ab3": {"id": "507a28ae-df7d-45e3-8499-0c1c04631ab3", "created_at": "2022-11-01T07:27:27.186646", "updated_at": "2022-11-01T07:27:27.186646", "first_name": "Betty", "last_name": "Bar", "email": "airbnb@mail.com", "password": "root", "__class__": "User"}, "User.be6a899c-f5f0-428a-9be3-0954afecc460": {"id": "be6a899c-f5f0-428a-9be3-0954afecc460", "created_at": "2022-11-01T07:27:27.196409", "updated_at": "2022-11-01T07:27:27.196409", "first_name": "John", "email": "airbnb2@mail.com", "password": "root", "__class__": "User"}}